[
  {
    "id": "18.05.02",
    "nama": "Menggala"
  },
  {
    "id": "18.05.06",
    "nama": "Gedung Aji"
  },
  {
    "id": "18.05.08",
    "nama": "Banjar Agung"
  },
  {
    "id": "18.05.11",
    "nama": "Gedung Meneng"
  },
  {
    "id": "18.05.12",
    "nama": "Rawa Jitu Selatan (Rawajitu Selatan)"
  },
  {
    "id": "18.05.13",
    "nama": "Penawar Tama"
  },
  {
    "id": "18.05.18",
    "nama": "Rawa Jitu Timur (Rawajitu Timur)"
  },
  {
    "id": "18.05.20",
    "nama": "Banjar Margo"
  },
  {
    "id": "18.05.22",
    "nama": "Rawa Pitu"
  },
  {
    "id": "18.05.23",
    "nama": "Penawar Aji"
  },
  {
    "id": "18.05.25",
    "nama": "Dente Teladas"
  },
  {
    "id": "18.05.26",
    "nama": "Meraksa Aji"
  },
  {
    "id": "18.05.27",
    "nama": "Gedung Aji Baru"
  },
  {
    "id": "18.05.29",
    "nama": "Banjar Baru"
  },
  {
    "id": "18.05.30",
    "nama": "Menggala Timur"
  }
]