[
  {
    "id": "21.04.01",
    "nama": "Singkep"
  },
  {
    "id": "21.04.02",
    "nama": "Lingga"
  },
  {
    "id": "21.04.03",
    "nama": "Senayang"
  },
  {
    "id": "21.04.04",
    "nama": "Singkep Barat"
  },
  {
    "id": "21.04.05",
    "nama": "Lingga Utara"
  },
  {
    "id": "21.04.06",
    "nama": "Singkep Pesisir"
  },
  {
    "id": "21.04.07",
    "nama": "Lingga Timur"
  },
  {
    "id": "21.04.08",
    "nama": "Selayar"
  },
  {
    "id": "21.04.09",
    "nama": "Singkep Selatan"
  },
  {
    "id": "21.04.10",
    "nama": "Kepulauan Posek"
  },
  {
    "id": "21.04.11",
    "nama": "Katang Bidare"
  },
  {
    "id": "21.04.12",
    "nama": "Temiang Pesisir"
  },
  {
    "id": "21.04.13",
    "nama": "Bakung Serumpun"
  }
]