[
  {
    "id": "53.11.01",
    "nama": "Kota Waingapu"
  },
  {
    "id": "53.11.02",
    "nama": "Haharu"
  },
  {
    "id": "53.11.03",
    "nama": "Lewa"
  },
  {
    "id": "53.11.04",
    "nama": "Nggaha Ori Angu (Nggaha Oriangu)"
  },
  {
    "id": "53.11.05",
    "nama": "Tabundung"
  },
  {
    "id": "53.11.06",
    "nama": "Pinu Pahar (Pinupahar / Pirapahar)"
  },
  {
    "id": "53.11.07",
    "nama": "Pandawai"
  },
  {
    "id": "53.11.08",
    "nama": "Umalulu"
  },
  {
    "id": "53.11.09",
    "nama": "Rindi"
  },
  {
    "id": "53.11.10",
    "nama": "Pahunga Lodu"
  },
  {
    "id": "53.11.11",
    "nama": "Wulla Waijelu (Wula Waijelu)"
  },
  {
    "id": "53.11.12",
    "nama": "Paberiwai"
  },
  {
    "id": "53.11.13",
    "nama": "Karera"
  },
  {
    "id": "53.11.14",
    "nama": "Kahaungu Eti (Kahaunguweti)"
  },
  {
    "id": "53.11.15",
    "nama": "Matawai La Pawu (Lappau)"
  },
  {
    "id": "53.11.16",
    "nama": "Kambera"
  },
  {
    "id": "53.11.17",
    "nama": "Kambata Mapambuhang"
  },
  {
    "id": "53.11.18",
    "nama": "Lewa Tidahu"
  },
  {
    "id": "53.11.19",
    "nama": "Katala Hamu Lingu"
  },
  {
    "id": "53.11.20",
    "nama": "Kanatang"
  },
  {
    "id": "53.11.21",
    "nama": "Ngadu Ngala"
  },
  {
    "id": "53.11.22",
    "nama": "Mahu"
  }
]