[
  {
    "id": "82.03.04",
    "nama": "Galela"
  },
  {
    "id": "82.03.05",
    "nama": "Tobelo"
  },
  {
    "id": "82.03.06",
    "nama": "Tobelo Selatan"
  },
  {
    "id": "82.03.07",
    "nama": "Kao"
  },
  {
    "id": "82.03.08",
    "nama": "Malifut"
  },
  {
    "id": "82.03.09",
    "nama": "Loloda Utara"
  },
  {
    "id": "82.03.10",
    "nama": "Tobelo Utara"
  },
  {
    "id": "82.03.11",
    "nama": "Tobelo Tengah"
  },
  {
    "id": "82.03.12",
    "nama": "Tobelo Timur"
  },
  {
    "id": "82.03.13",
    "nama": "Tobelo Barat"
  },
  {
    "id": "82.03.14",
    "nama": "Galela Barat"
  },
  {
    "id": "82.03.15",
    "nama": "Galela Utara"
  },
  {
    "id": "82.03.16",
    "nama": "Galela Selatan"
  },
  {
    "id": "82.03.19",
    "nama": "Loloda Kepulauan"
  },
  {
    "id": "82.03.20",
    "nama": "Kao Utara"
  },
  {
    "id": "82.03.21",
    "nama": "Kao Barat"
  },
  {
    "id": "82.03.22",
    "nama": "Kao Teluk"
  }
]