[
  {
    "id": "91.10.01",
    "nama": "Sarmi"
  },
  {
    "id": "91.10.02",
    "nama": "Tor Atas"
  },
  {
    "id": "91.10.03",
    "nama": "Pantai Barat"
  },
  {
    "id": "91.10.04",
    "nama": "Pantai Timur"
  },
  {
    "id": "91.10.05",
    "nama": "Bonggo"
  },
  {
    "id": "91.10.09",
    "nama": "Apawer Hulu"
  },
  {
    "id": "91.10.12",
    "nama": "Sarmi Selatan"
  },
  {
    "id": "91.10.13",
    "nama": "Sarmi Timur"
  },
  {
    "id": "91.10.14",
    "nama": "Pantai Timur Bagian Barat"
  },
  {
    "id": "91.10.15",
    "nama": "Bonggo Timur"
  }
]