[
  {
    "id": "14.01.08.1001",
    "nama": "Sungai Pagar"
  },
  {
    "id": "14.01.08.2002",
    "nama": "Mentulik"
  },
  {
    "id": "14.01.08.2003",
    "nama": "Sungai Simpang Dua"
  },
  {
    "id": "14.01.08.2004",
    "nama": "Sungai Bunga/Bungo"
  },
  {
    "id": "14.01.08.2005",
    "nama": "Rantau Kasih"
  },
  {
    "id": "14.01.08.2006",
    "nama": "Sungai Petai"
  },
  {
    "id": "14.01.08.2007",
    "nama": "Gading Permai"
  },
  {
    "id": "14.01.08.2008",
    "nama": "Bangun Sari"
  }
]