[
  {
    "id": "16.03.11.2001",
    "nama": "Pinang Belarik"
  },
  {
    "id": "16.03.11.2002",
    "nama": "Ujan Mas Lama"
  },
  {
    "id": "16.03.11.2003",
    "nama": "Ujan Mas Baru"
  },
  {
    "id": "16.03.11.2004",
    "nama": "Tanjung Raman"
  },
  {
    "id": "16.03.11.2005",
    "nama": "Muara Gula Baru"
  },
  {
    "id": "16.03.11.2006",
    "nama": "Muara Gula Lama"
  },
  {
    "id": "16.03.11.2007",
    "nama": "Guci"
  },
  {
    "id": "16.03.11.2008",
    "nama": "Ulak Bandung"
  }
]