[
  {
    "id": "33.14.17.2001",
    "nama": "Newung"
  },
  {
    "id": "33.14.17.2002",
    "nama": "Jatitengah (Jati Tengah)"
  },
  {
    "id": "33.14.17.2003",
    "nama": "Bendo"
  },
  {
    "id": "33.14.17.2004",
    "nama": "Juwok"
  },
  {
    "id": "33.14.17.2005",
    "nama": "Pantirejo"
  },
  {
    "id": "33.14.17.2006",
    "nama": "Majenang"
  },
  {
    "id": "33.14.17.2007",
    "nama": "Karanganom (Karang Anom)"
  },
  {
    "id": "33.14.17.2008",
    "nama": "Gebang"
  },
  {
    "id": "33.14.17.2009",
    "nama": "Baleharjo"
  }
]