[
  {
    "id": "35.29.22.2001",
    "nama": "Ketupat"
  },
  {
    "id": "35.29.22.2002",
    "nama": "Jungkat"
  },
  {
    "id": "35.29.22.2003",
    "nama": "Kropoh (Karopoh)"
  },
  {
    "id": "35.29.22.2004",
    "nama": "Karangnangka"
  },
  {
    "id": "35.29.22.2005",
    "nama": "Alas Malang (Alasmalang)"
  },
  {
    "id": "35.29.22.2006",
    "nama": "Poteran"
  },
  {
    "id": "35.29.22.2007",
    "nama": "Brakas"
  },
  {
    "id": "35.29.22.2008",
    "nama": "Tonduk"
  },
  {
    "id": "35.29.22.2009",
    "nama": "Guwa Guwa"
  }
]