[
  {
    "id": "63.04.09.2001",
    "nama": "Sei/Sungai Kambat"
  },
  {
    "id": "63.04.09.2002",
    "nama": "Sei/Sungai Rasau"
  },
  {
    "id": "63.04.09.2003",
    "nama": "Simpang Nungki"
  },
  {
    "id": "63.04.09.2004",
    "nama": "Sawahan"
  },
  {
    "id": "63.04.09.2005",
    "nama": "Bantuil"
  },
  {
    "id": "63.04.09.2006",
    "nama": "Badandan"
  },
  {
    "id": "63.04.09.2007",
    "nama": "Sei/Sungai Tunjang"
  },
  {
    "id": "63.04.09.2008",
    "nama": "Sei/Sungai Raya"
  }
]