[
  {
    "id": "73.06.15.2001",
    "nama": "Julumate'ne"
  },
  {
    "id": "73.06.15.2002",
    "nama": "Bontolempangang (Bontolempangan)"
  },
  {
    "id": "73.06.15.2003",
    "nama": "Lassa Lassa"
  },
  {
    "id": "73.06.15.2004",
    "nama": "Bontoloe"
  },
  {
    "id": "73.06.15.2005",
    "nama": "Pa'ladingang"
  },
  {
    "id": "73.06.15.2006",
    "nama": "Paranglompoa (Parang Lampoa)"
  },
  {
    "id": "73.06.15.2007",
    "nama": "Bontotangnga"
  },
  {
    "id": "73.06.15.2008",
    "nama": "Ulujangang (Ulujangan)"
  }
]