[
  {
    "id": "73.05.07.1001",
    "nama": "Pattallassang"
  },
  {
    "id": "73.05.07.1002",
    "nama": "Pallantikang"
  },
  {
    "id": "73.05.07.1003",
    "nama": "Somba Bella (Sombabella)"
  },
  {
    "id": "73.05.07.1004",
    "nama": "Kalabbirang"
  },
  {
    "id": "73.05.07.1005",
    "nama": "Maradekaya (Mardekaya)"
  },
  {
    "id": "73.05.07.1006",
    "nama": "Pappa"
  },
  {
    "id": "73.05.07.1007",
    "nama": "Bajeng"
  },
  {
    "id": "73.05.07.1008",
    "nama": "Sabintang"
  },
  {
    "id": "73.05.07.1009",
    "nama": "Salaka"
  }
]