[
  {
    "id": "74.06.10.2001",
    "nama": "Tampawulu (Tanpabulu)"
  },
  {
    "id": "74.06.10.2002",
    "nama": "Tanah Poleang"
  },
  {
    "id": "74.06.10.2003",
    "nama": "Karya Baru"
  },
  {
    "id": "74.06.10.2004",
    "nama": "Toburi"
  },
  {
    "id": "74.06.10.2005",
    "nama": "Rompu Rompu"
  },
  {
    "id": "74.06.10.2006",
    "nama": "Pulau Ea (Es)"
  },
  {
    "id": "74.06.10.2007",
    "nama": "Lawatu Ea (Es)"
  },
  {
    "id": "74.06.10.2008",
    "nama": "Wambarema"
  }
]