[
  {
    "id": "74.02.21.1003",
    "nama": "Laosu"
  },
  {
    "id": "74.02.21.2002",
    "nama": "Pebunooha"
  },
  {
    "id": "74.02.21.2004",
    "nama": "Lalonggalaku (Lalonggaluku)"
  },
  {
    "id": "74.02.21.2009",
    "nama": "Diolo"
  },
  {
    "id": "74.02.21.2018",
    "nama": "Pebunooha Dalam"
  },
  {
    "id": "74.02.21.2023",
    "nama": "Rumbia"
  },
  {
    "id": "74.02.21.2028",
    "nama": "Rambu Kongga"
  },
  {
    "id": "74.02.21.2029",
    "nama": "Laosu Jaya"
  },
  {
    "id": "74.02.21.2031",
    "nama": "Langgaluku Timur (Lalonggaluku Timur)"
  }
]