[
  {
    "id": "82.03.11.2001",
    "nama": "Upa"
  },
  {
    "id": "82.03.11.2002",
    "nama": "Pitu"
  },
  {
    "id": "82.03.11.2003",
    "nama": "Wosi (Wosia)"
  },
  {
    "id": "82.03.11.2004",
    "nama": "WKO"
  },
  {
    "id": "82.03.11.2005",
    "nama": "Kalipitu"
  },
  {
    "id": "82.03.11.2006",
    "nama": "Kali Upa"
  },
  {
    "id": "82.03.11.2007",
    "nama": "Lina Ino"
  },
  {
    "id": "82.03.11.2008",
    "nama": "Mahia (Wosi/Wosia Tengah)"
  },
  {
    "id": "82.03.11.2009",
    "nama": "Tanjung Niara (Wosi/Wosia Selatan)"
  }
]