[
  {
    "id": "95.01.20.2001",
    "nama": "Siepkosi"
  },
  {
    "id": "95.01.20.2002",
    "nama": "Yumogima (Isibitlah)"
  },
  {
    "id": "95.01.20.2003",
    "nama": "Sekan"
  },
  {
    "id": "95.01.20.2004",
    "nama": "Noagalo"
  },
  {
    "id": "95.01.20.2005",
    "nama": "Manika"
  },
  {
    "id": "95.01.20.2006",
    "nama": "Sekan Dalam"
  },
  {
    "id": "95.01.20.2007",
    "nama": "Isawa Himan"
  },
  {
    "id": "95.01.20.2008",
    "nama": "Lunaima"
  },
  {
    "id": "95.01.20.2009",
    "nama": "Wekia"
  }
]